vibetrimright/__init__.py
vibetrimright/ai.py
vibetrimright/py.typed
vibetrimright-0.1.1.dist-info/METADATA
vibetrimright-0.1.1.dist-info/WHEEL
vibetrimright-0.1.1.dist-info/licenses/LICENSE
vibetrimright-0.1.1.dist-info/RECORD
