Metadata-Version: 2.4
Name: vibetrimright
Version: 0.1.1
Summary: String right-trimming library that uses GPT to remove trailing whitespace
Author-email: Taha Parker <tahayparker@gmail.com>
License-File: LICENSE
Requires-Python: >=3.10
Requires-Dist: openai>=1.95.1
Requires-Dist: pydantic>=2.11.7
Requires-Dist: typing-extensions>=4.14.1
